plus_error.py
plus_error-1.2.dist-info/METADATA
plus_error-1.2.dist-info/WHEEL
plus_error-1.2.dist-info/top_level.txt
plus_error-1.2.dist-info/RECORD
