Metadata-Version: 2.1
Name: plus-error
Version: 1.2
Summary: This module helps you to squash bugs by giving you information about the error and how to fix it.
Home-page: https://github.com/RealPenguin12/plus_error
Author: TheRealPenguin12
Requires-Dist: termcolor
